ImportanceScore/ImportanceScore/__init__.py
ImportanceScore/ImportanceScore/csv_table.py
ImportanceScore/ImportanceScore/custom_editor.py
ImportanceScore/ImportanceScore/data_loader.py
ImportanceScore/ImportanceScore/features.py
ImportanceScore/ImportanceScore/importance_rank.py
ImportanceScore/ImportanceScore/importance_schema.py
ImportanceScore/ImportanceScore/manifest.py
ImportanceScore/ImportanceScore/model.py
ImportanceScore/ImportanceScore/predict_model.py
ImportanceScore/ImportanceScore/project_paths.py
ImportanceScore/ImportanceScore/text_weight_scoring.py
ImportanceScore/ImportanceScore/train_model.py
ImportanceScore/ImportanceScore/transformations.py
ImportanceScore/ImportanceScore/tune_model.py
ImportanceScore/ImportanceScore/weighted_linear_model.py
ImportanceScore/ImportanceScore/resources/__init__.py
ImportanceScore/tests/text_benchmark.py
importancescore-1.1.2.dist-info/licenses/LICENSE
importancescore-1.1.2.dist-info/METADATA
importancescore-1.1.2.dist-info/WHEEL
importancescore-1.1.2.dist-info/entry_points.txt
importancescore-1.1.2.dist-info/top_level.txt
importancescore-1.1.2.dist-info/RECORD
