Metadata-Version: 2.4
Name: ImportanceScore
Version: 1.1.2
Summary: A tool for creating heuristic and ML-based importance scores.
Author: corb
License: Copyright 2025 corb555
Project-URL: Repository, https://github.com/corb555/ImportanceScore
Keywords: machine learning,scoring,ranking
Classifier: Development Status :: 4 - Beta
Classifier: Intended Audience :: Developers
Classifier: Intended Audience :: Science/Research
Classifier: License :: OSI Approved :: MIT License
Classifier: Operating System :: POSIX :: Linux
Classifier: Operating System :: MacOS
Classifier: Programming Language :: Python :: 3.9
Classifier: Programming Language :: Python :: 3.10
Classifier: Programming Language :: Python :: 3.11
Classifier: Topic :: Scientific/Engineering :: GIS
Classifier: Topic :: Software Development :: Libraries :: Python Modules
Requires-Python: >=3.9
License-File: LICENSE
Requires-Dist: joblib~=1.4
Requires-Dist: pandas~=2.2
Requires-Dist: scikit-learn~=1.5
Requires-Dist: flashtext~=2.7
Requires-Dist: YMLEditor>=0.6
Provides-Extra: tuning
Requires-Dist: optuna~=3.5; extra == "tuning"
Provides-Extra: viz
Requires-Dist: matplotlib~=3.8; extra == "viz"
Provides-Extra: explain
Requires-Dist: shap~=0.45; extra == "explain"
Provides-Extra: dev
Requires-Dist: pytest; extra == "dev"
Requires-Dist: pytest-mock; extra == "dev"
Dynamic: license-file
